aiogqlc/__init__.py
aiogqlc/client.py
aiogqlc/constants.py
aiogqlc/errors.py
aiogqlc/py.typed
aiogqlc/types.py
aiogqlc/utils.py
aiogqlc-5.4.0.dist-info/METADATA
aiogqlc-5.4.0.dist-info/WHEEL
aiogqlc-5.4.0.dist-info/licenses/LICENSE
aiogqlc-5.4.0.dist-info/RECORD
